{
    "images":
    {
        "bg":
        {
            "image" : "paracraft:bg.png",
            "posX" : -30,
            "posY" : -270,
            "width" : 960,
            "height" : 540,
            "alignment" : "left_center"
        },

        "title":
        {
            "image" : "paracraft:paracraft.png",
            "posX" : 40,
            "posY" : -150,
            "width" : 216,
            "height" : 42,
            "alignment" : "left_center"
        }
    },
    
    "buttons":
    {
        "singleplayer":
        {
            "text" : "menu.singleplayer",
            "posX" : 80,
            "posY" : -50,
            "width" : 130,
            "height" : 30,
            "action" : 
            {
                "type" : "openGui",
                "gui" : "singleplayer"
            },
            "texture" : "paracraft:btn.png",
            "alignment" : "left_center",
            "normalTextColor" : 16777215,
            "hoverTextColor" : 16777215
        },
        
        "multiplayer":
        {
            "text" : "menu.multiplayer",
            "posX" : 80,
            "posY" : -10,
            "width" : 130,
            "height" : 30,
            "action" : 
            {
                "type" : "openGui",
                "gui" : "multiplayer"
            },
            "texture" : "paracraft:btn.png",
            "alignment" : "left_center",
            "normalTextColor" : 16777215,
            "hoverTextColor" : 16777215
        },
        
        "mods":
        {
            "text" : "fml.menu.mods",
            "posX" : 80,
            "posY" : 30,
            "width" : 60,
            "height" : 30,
            "action" : 
            {
                "type" : "openGui",
                "gui" : "mods"
            },
            "texture" : "paracraft:btn2.png",
            "alignment" : "left_center",
            "normalTextColor" : 16777215,
            "hoverTextColor" : 16777215
        },
            
        "options":
        {
            "text" : "menu.options",
            "posX" : 150,
            "posY" : 30,
            "width" : 60,
            "height" : 30,
            "action" : 
            {
                "type" : "openGui",
                "gui" : "options"
            },
            "texture" : "paracraft:btn2.png",
            "alignment" : "left_center",
            "normalTextColor" : 16777215,
            "hoverTextColor" : 16777215
        }
    },
    
    "labels":
    {
        "mojang":
        {
            "text" : "Copyright Mojang AB. Do not distribute!",
            "hoverText" : "Œ“∞Æ–°∫Æ~",
            "posX" : -140,
            "posY" : -10,
            "color" : -1,
            "alignment" : "bottom_right",
            "action" : 
            {
                "type" : "openGui",
                "gui" : "credits"
            }
        },
        
        "fml":
        {
            "text" : "",
            "posX" : 2,
            "posY" : -46,
            "color" : -1,
            "alignment" : "bottom_left"
        }
    },
    
    "other":
    {
        "splash-text":
        {
            "posX" : 240,
            "posY" : -110,
            "color" : -256,
            "alignment" : "left_center",
            "texts" : "file:minecraft:texts/splashes.txt"
        },
        
        "background":
        {
            "image" : "",
            "slideshow":
            {
                "images" : ["paracraft:bg_1.png","paracraft:bg_2.png","paracraft:bg_3.png","paracraft:bg_4.png","paracraft:bg_5.png","paracraft:bg_6.png","paracraft:bg_7.png"],
                "displayDuration" : 100,
                "fadeDuration" : 40
                }
            }
    }
}